tygenie/__init__.py
tygenie/app.py
tygenie/config.py
tygenie/consts.py
tygenie/logger.py
tygenie/opsgenie.py
tygenie/screen.py
tygenie/tygenie.tcss
tygenie/alert_details/__init__.py
tygenie/alert_details/description_formatter.py
tygenie/alerts_list/__init__.py
tygenie/alerts_list/formatter.py
tygenie/custom_actions/__init__.py
tygenie/custom_actions/custom_action.py
tygenie/custom_actions/example.py
tygenie/opsgenie_rest_api_client/__init__.py
tygenie/opsgenie_rest_api_client/client.py
tygenie/opsgenie_rest_api_client/errors.py
tygenie/opsgenie_rest_api_client/py.typed
tygenie/opsgenie_rest_api_client/types.py
tygenie/opsgenie_rest_api_client/api/__init__.py
tygenie/opsgenie_rest_api_client/api/account/__init__.py
tygenie/opsgenie_rest_api_client/api/account/get_info.py
tygenie/opsgenie_rest_api_client/api/alert/__init__.py
tygenie/opsgenie_rest_api_client/api/alert/acknowledge_alert.py
tygenie/opsgenie_rest_api_client/api/alert/add_attachment.py
tygenie/opsgenie_rest_api_client/api/alert/add_details.py
tygenie/opsgenie_rest_api_client/api/alert/add_note.py
tygenie/opsgenie_rest_api_client/api/alert/add_responder.py
tygenie/opsgenie_rest_api_client/api/alert/add_tags.py
tygenie/opsgenie_rest_api_client/api/alert/add_team.py
tygenie/opsgenie_rest_api_client/api/alert/assign_alert.py
tygenie/opsgenie_rest_api_client/api/alert/close_alert.py
tygenie/opsgenie_rest_api_client/api/alert/count_alerts.py
tygenie/opsgenie_rest_api_client/api/alert/create_alert.py
tygenie/opsgenie_rest_api_client/api/alert/create_saved_searches.py
tygenie/opsgenie_rest_api_client/api/alert/delete_alert.py
tygenie/opsgenie_rest_api_client/api/alert/delete_saved_search.py
tygenie/opsgenie_rest_api_client/api/alert/escalate_alert.py
tygenie/opsgenie_rest_api_client/api/alert/execute_custom_alert_action.py
tygenie/opsgenie_rest_api_client/api/alert/get_alert.py
tygenie/opsgenie_rest_api_client/api/alert/get_attachment.py
tygenie/opsgenie_rest_api_client/api/alert/get_request_status.py
tygenie-1.14.0.dist-info/METADATA
tygenie-1.14.0.dist-info/WHEEL
tygenie-1.14.0.dist-info/entry_points.txt
tygenie-1.14.0.dist-info/licenses/AUTHORS
tygenie-1.14.0.dist-info/licenses/LICENSE
tygenie-1.14.0.dist-info/RECORD
