Metadata-Version: 2.4
Name: tygenie
Version: 1.14.0
Summary: Tygenie is an Opsgenie TUI application
Project-URL: Homepage, https://github.com/ovh/tygenie
Author-email: Pierre-Samuel Le Stang <pierre-samuel.le-stang@corp.ovh.com>
License:    Copyright 2024 OVHcloud
License-File: AUTHORS
License-File: LICENSE
Requires-Python: >=3.11
Requires-Dist: attrs==24.2.0
Requires-Dist: desktop-notifier==5.0.1
Requires-Dist: httpx==0.27.2
Requires-Dist: markdownify==0.14.1
Requires-Dist: pendulum==3.0.0
Requires-Dist: python-dateutil==2.9.0.post0
Requires-Dist: rich==14.2.0
Requires-Dist: semver==3.0.1
Requires-Dist: textual[syntax]==6.12.0
Requires-Dist: udatetime==0.0.17
Requires-Dist: urllib3==2.5.0
